README.md
setup.py
virtualvideo/__init__.py
virtualvideo/devices.py
virtualvideo.egg-info/PKG-INFO
virtualvideo.egg-info/SOURCES.txt
virtualvideo.egg-info/dependency_links.txt
virtualvideo.egg-info/requires.txt
virtualvideo.egg-info/top_level.txt