Metadata-Version: 2.1
Name: virtualvideo
Version: 0.1.6
Summary: virtualvideo allows you to write simple programs
Home-page: https://github.com/Flashs/virtualvideo
Author: Flashs
License: GPLv3
Platform: UNKNOWN
Classifier: Development Status :: 3 - Alpha
Classifier: Environment :: Console
Classifier: Topic :: System :: Operating System Kernels :: Linux
Classifier: Topic :: Multimedia :: Video :: Display
Classifier: License :: OSI Approved :: GNU General Public License v3 or later (GPLv3+)
Requires-Python: >=3.6
